blotter/__init__.py
blotter/__main__.py
blotter/blot.py
blotter/directions.py
blotter/fill.py
blotter/input.py
blotter/log.py
blotter/util.py
blotter-1.17.dist-info/METADATA
blotter-1.17.dist-info/WHEEL
blotter-1.17.dist-info/top_level.txt
blotter-1.17.dist-info/RECORD
