Metadata-Version: 2.1
Name: blotter
Version: 1.17
Summary: trade blotting profit and loss calculator
Home-page: UNKNOWN
Author: Andrew Berger
Author-email: aberger91@pm.me
License: UNKNOWN
Platform: UNKNOWN
